COPYING
MANIFEST.in
README
pyinputstats
pyinputstats.desktop
setup.py
pygtk_chart/__init__.py
pygtk_chart/bar_chart.py
pygtk_chart/basics.py
pygtk_chart/chart.py
pygtk_chart/chart_object.py
pygtk_chart/label.py
pygtk_chart/line_chart.py
pygtk_chart/multi_bar_chart.py
pygtk_chart/pie_chart.py
pyinputstats.egg-info/PKG-INFO
pyinputstats.egg-info/SOURCES.txt
pyinputstats.egg-info/dependency_links.txt
pyinputstats.egg-info/requires.txt
pyinputstats.egg-info/top_level.txt
pyinputstatsmodules/__init__.py
pyinputstatsmodules/__init__.pyc
pyinputstatsmodules/collector.py
pyinputstatsmodules/collector.pyc
pyinputstatsmodules/database.py
pyinputstatsmodules/database.pyc
pyinputstatsmodules/gui.py
pyinputstatsmodules/gui.pyc
pyinputstatsmodules/helpers.py
pyinputstatsmodules/helpers.pyc
pyinputstatsmodules/__pycache__/__init__.cpython-32.pyc
pyinputstatsmodules/glade/gui _old_v1.glade
pyinputstatsmodules/glade/gui.glade
pyinputstatsmodules/images/1277530791.png
pyinputstatsmodules/images/Anonymous_keyboard_key.png
pyinputstatsmodules/images/babayasin_Hand_cursor.png
pyinputstatsmodules/images/ruler.png
pyinputstatsmodules/images/ruler14.png
pyinputstatsmodules/images/ruler192.png
pyinputstatsmodules/images/ruler64.png
pyinputstatsmodules/images/tacho_meter32.png