Metadata-Version: 1.0
Name: pyinputstats
Version: 0.2.1.3
Summary: An application for keyboard and mouse statistics
Home-page: http://launchpad.net/pyinputstats
Author: Daniel Nögel
Author-email: pyinputstats@post.danielnoegel.de
License: GPLv3
Keywords: keyboard mouse statistics
Platform: UNKNOWN
Classifier: Development Status :: 4 - Beta
Classifier: Topic :: Utilities
Classifier: License :: OSI Approved :: GNU General Public License (GPL)
Classifier: Programming Language :: Python
